smgenerator/SMGen_multi.py
smgenerator/SMGen_one.py
smgenerator/__init__.py
smgenerator/_version.py
smgenerator/cli/__init__.py
smgenerator/cli/smgenerator.py
smgenerator/data/exit.png
smgenerator/data/gui.ui
smgenerator/data/load.png
smgenerator/data/new.png
smgenerator/data/save.png
smgenerator/smgenerator/SMGen_multi.py
smgenerator/smgenerator/SMGen_one.py
smgenerator/smgenerator/__init__.py
smgenerator/smgenerator/_version.py
smgenerator/smgenerator/cli/__init__.py
smgenerator/smgenerator/cli/smgenerator.py
smgenerator-0.1.1.dist-info/LICENSE
smgenerator-0.1.1.dist-info/METADATA
smgenerator-0.1.1.dist-info/WHEEL
smgenerator-0.1.1.dist-info/entry_points.txt
smgenerator-0.1.1.dist-info/top_level.txt
smgenerator-0.1.1.dist-info/RECORD
