Metadata-Version: 2.1
Name: smgenerator
Version: 0.1.1
Summary: Synthetic Models of biological systems Generator
Home-page: https://gitlab.com/sgr34/smgen
Author: Simone G. Riva
Author-email: simo.riva15@gmail.com
License: LICENCE
Keywords: Synthetic Models,Reaction-based Models,Biochemical Networks,Systems Biology
Platform: UNKNOWN
Classifier: Programming Language :: Python :: 3
Classifier: Programming Language :: Python :: 3.5
Classifier: Programming Language :: Python :: 3.6
Classifier: Programming Language :: Python :: 3.7
Classifier: Programming Language :: Python :: 3.8
Classifier: Programming Language :: Python :: 3.9
Requires-Python: >=3.5
License-File: LICENSE
Requires-Dist: numpy (>=1.21.2)
Requires-Dist: python-libsbml (>=5.19.0)
Requires-Dist: matplotlib (>=3.4.3)
Requires-Dist: networkx (>=2.6.3)
Requires-Dist: PyQt5 (>=5.15.5)
